comment_scanner/__init__.py
comment_scanner/comment_scanner.py
comment_scanner/parsers/__init__.py
comment_scanner/parsers/c_parser.py
comment_scanner/parsers/common.py
comment_scanner/parsers/js_parser.py
comment_scanner/parsers/python_parser.py
comment_scanner-0.4.dist-info/LICENSE
comment_scanner-0.4.dist-info/METADATA
comment_scanner-0.4.dist-info/WHEEL
comment_scanner-0.4.dist-info/entry_points.txt
comment_scanner-0.4.dist-info/top_level.txt
comment_scanner-0.4.dist-info/RECORD
