Metadata-Version: 2.1
Name: comment-scanner
Version: 0.4
Summary: Parse comments from various source code files
Home-page: https://github.com/FaizAlam/comment-scanner
Author: Faiz Alam
Author-email: mohdfaizalam53@gmail.com
Classifier: Development Status :: 4 - Beta
Classifier: Programming Language :: Python :: 3
Classifier: Topic :: Software Development :: Documentation
Classifier: License :: OSI Approved :: MIT License
Classifier: Operating System :: OS Independent
Requires-Python: >=3.7
License-File: LICENSE
Requires-Dist: python-magic-bin >=0.4.14
